pyrailroad/__init__.py
pyrailroad/cli.py
pyrailroad/defaults.py
pyrailroad/elements.py
pyrailroad/exceptions.py
pyrailroad/parser.py
pyrailroad/utils.py
pyrailroad/style/default.css
pyrailroad-0.3.2.dist-info/LICENSE
pyrailroad-0.3.2.dist-info/METADATA
pyrailroad-0.3.2.dist-info/WHEEL
pyrailroad-0.3.2.dist-info/entry_points.txt
pyrailroad-0.3.2.dist-info/top_level.txt
pyrailroad-0.3.2.dist-info/RECORD
