Metadata-Version: 2.1
Name: pyrailroad
Version: 0.3.2
Summary: Python package to draw railroad (or syntax) diagrams. Based largely on railroad-daigram and the partial parser by tbatkins.
Author-email: Rafael Lopez <rafael.lopez@universite-paris-saclay.fr>
License: MIT
Keywords: railroad,diagram
Classifier: Programming Language :: Python :: 3
Requires-Python: >=3.10
License-File: LICENSE
Requires-Dist: typer[all]
Requires-Dist: pyyaml
Requires-Dist: mkdocs
Requires-Dist: mkdocs-material
Provides-Extra: tests
Requires-Dist: pytest ; extra == 'tests'
Requires-Dist: coverage ; extra == 'tests'
